Advancedconsole.py
AdvancedConsole-1.7.dist-info/LICENSE.txt
AdvancedConsole-1.7.dist-info/METADATA
AdvancedConsole-1.7.dist-info/WHEEL
AdvancedConsole-1.7.dist-info/top_level.txt
AdvancedConsole-1.7.dist-info/RECORD
