Metadata-Version: 2.1
Name: AdvancedConsole
Version: 1.7
Summary: UNKNOWN
Home-page: https://github.com/jack-the-hack/AdvancedConsole
Author: Donnie Jack Baldyga
License: UNKNOWN
Platform: UNKNOWN
Classifier: Programming Language :: Python :: 3
Classifier: License :: OSI Approved :: MIT License
Requires-Dist: keyboard
